odoo/addons/pos_warning_exiting/README.rst
odoo/addons/pos_warning_exiting/__init__.py
odoo/addons/pos_warning_exiting/__manifest__.py
odoo/addons/pos_warning_exiting/i18n/fr.po
odoo/addons/pos_warning_exiting/i18n/pos_warning_exiting.pot
odoo/addons/pos_warning_exiting/readme/CONTRIBUTORS.rst
odoo/addons/pos_warning_exiting/readme/DESCRIPTION.rst
odoo/addons/pos_warning_exiting/static/description/icon.png
odoo/addons/pos_warning_exiting/static/description/index.html
odoo/addons/pos_warning_exiting/static/description/pos_warning_connection_lost.png
odoo/addons/pos_warning_exiting/static/description/pos_warning_unpaid_draft_orders.png
odoo/addons/pos_warning_exiting/static/src/js/gui.js
odoo/addons/pos_warning_exiting/views/templates.xml
odoo12_addon_pos_warning_exiting-12.0.1.0.2.dist-info/METADATA
odoo12_addon_pos_warning_exiting-12.0.1.0.2.dist-info/WHEEL
odoo12_addon_pos_warning_exiting-12.0.1.0.2.dist-info/top_level.txt
odoo12_addon_pos_warning_exiting-12.0.1.0.2.dist-info/RECORD
